ddiscord
