Metadata-Version: 2.1
Name: ddiscord
Version: 0.2.3
Summary: Debugger for discord.py
Home-page: https://github.com/aiotter/ddiscord
Author: aiotter
Author-email: ogran.std@gmail.com
License: MIT
Platform: UNKNOWN
Classifier: Development Status :: 3 - Alpha
Classifier: Intended Audience :: Developers
Classifier: Programming Language :: Python :: 3.6
Classifier: Programming Language :: Python :: 3.7
Requires-Python: >=3.6, <4
